nyx/__init__.py
nyx/_rust_core.cpython-310-x86_64-linux-gnu.so
nyx/assets.py
nyx/client.py
nyx/solana_client.py
nyx/token_utils.py
nyx/types.py
nyx/utils.py
nyx/x402/__init__.py
nyx/x402/client.py
nyx/x402/facilitator.py
nyx/x402/networks.py
nyx/x402/types.py
nyx_privacy-0.1.0.dist-info/METADATA
nyx_privacy-0.1.0.dist-info/WHEEL
nyx_privacy-0.1.0.dist-info/licenses/LICENSE
nyx_privacy-0.1.0.dist-info/RECORD
