Metadata-Version: 2.4
Name: nyx-privacy
Version: 0.1.0
Classifier: Intended Audience :: Developers
Classifier: License :: OSI Approved :: MIT License
Classifier: Programming Language :: Python :: 3.12
Classifier: Programming Language :: Rust
Classifier: Topic :: Security :: Cryptography
Classifier: Topic :: Software Development :: Libraries :: Python Modules
Requires-Dist: solana>=0.30.0
Requires-Dist: solders>=0.18.0
Requires-Dist: anchorpy>=0.18.0
Requires-Dist: base58>=2.1.1
Requires-Dist: pynacl>=1.5.0
Requires-Dist: httpx>=0.24.0
Requires-Dist: pydantic>=2.0.0
Requires-Dist: cryptography>=41.0.0
Requires-Dist: web3>=6.0.0
Requires-Dist: eth-account>=0.9.0
Requires-Dist: pytest>=7.4.0 ; extra == 'dev'
Requires-Dist: pytest-asyncio>=0.21.0 ; extra == 'dev'
Requires-Dist: pytest-cov>=4.1.0 ; extra == 'dev'
Requires-Dist: black>=23.0.0 ; extra == 'dev'
Requires-Dist: mypy>=1.0.0 ; extra == 'dev'
Requires-Dist: ruff>=0.1.0 ; extra == 'dev'
Requires-Dist: ipython>=8.0.0 ; extra == 'dev'
Requires-Dist: maturin>=1.4.0 ; extra == 'dev'
Provides-Extra: dev
License-File: LICENSE
Summary: Privacy SDK for Solana with optional x402 payment support - Python interface with Rust cryptographic backbone
Keywords: solana,privacy,zksnark,zero-knowledge,defi,sdk,x402,payments,cryptography
Author-email: Nyx Privacy Team <dev@nyxprivacy.tech>
License: MIT
Requires-Python: >=3.12
Project-URL: Homepage, https://nyxprivacy.tech
Project-URL: Documentation, https://nyxprivacy.tech/docs/getting-started/overview
Project-URL: Repository, https://github.com/nyxprivacy/nyx-privacy
Project-URL: Issues, https://github.com/nyxprivacy/nyx-privacy/issues
